Metadata-Version: 1.0
Name: lca-sweng
Version: 0.0.1
Summary: a Python module to return the lca of two given nodes
Home-page: UNKNOWN
Author: UNKNOWN
Author-email: UNKNOWN
License: UNKNOWN
Platform: UNKNOWN
